
COPYING.GPL
COPYING.TGPPL.html
README.rst
setup.py
stringchain/__init__.py
stringchain/_version.py
stringchain/stringchain.py
stringchain.egg-info/PKG-INFO
stringchain.egg-info/SOURCES.txt
stringchain.egg-info/dependency_links.txt
stringchain.egg-info/not-zip-safe
stringchain.egg-info/requires.txt
stringchain.egg-info/top_level.txt
stringchain/bench/__init__.py
stringchain/bench/bench.py
stringchain/test/__init__.py
stringchain/test/test_chain.py